{"name":"Verify all of the Laws \u0026 Regulations tabs from the EBSA page","testSteps":[{"number":1,"description":"[1] {lawsregsMenuItem\u003dHIPAA}","duration":9047,"startTime":1510687958568,"screenshots":[{"screenshot":"40a2f727b26a91e9d7cac3d687e8fb6e.png"}],"children":[{"number":2,"description":"Given the user is on the EBSA home page","duration":2450,"startTime":1510687958957,"screenshots":[{"screenshot":"40a2f727b26a91e9d7cac3d687e8fb6e.png"},{"screenshot":"27b89e7066e07b7b836933e6a1f8fe28.png"}],"result":"SUCCESS","children":[{"number":3,"description":"On EBSA page","duration":1565,"startTime":1510687959345,"screenshots":[{"screenshot":"40a2f727b26a91e9d7cac3d687e8fb6e.png"},{"screenshot":"90b06b0f195e6cd74b0026d3a4b3b0ea.png"}],"result":"SUCCESS"}]},{"number":4,"description":"When the user clicks on {HIPAA} within the Laws \u0026 Regulations tab on the menu bar","duration":4673,"startTime":1510687961407,"screenshots":[{"screenshot":"27b89e7066e07b7b836933e6a1f8fe28.png"},{"screenshot":"ecebda72f278ef6c026b455ca12c55ca.png"}],"result":"SUCCESS","children":[{"number":5,"description":"Click nav node: HIPAA","duration":3823,"startTime":1510687961902,"screenshots":[{"screenshot":"27b89e7066e07b7b836933e6a1f8fe28.png"},{"screenshot":"ecebda72f278ef6c026b455ca12c55ca.png"}],"result":"SUCCESS"}]},{"number":6,"description":"Then the {HIPAA} page should open correctly","duration":1535,"startTime":1510687966080,"screenshots":[{"screenshot":"ecebda72f278ef6c026b455ca12c55ca.png"}],"result":"SUCCESS","children":[{"number":7,"description":"Should see page: HIPAA","duration":806,"startTime":1510687966435,"screenshots":[{"screenshot":"ecebda72f278ef6c026b455ca12c55ca.png"}],"result":"SUCCESS"}]}]},{"number":8,"description":"[2] {lawsregsMenuItem\u003dfederalRegister}","duration":10783,"startTime":1510687967615,"screenshots":[{"screenshot":"ecebda72f278ef6c026b455ca12c55ca.png"}],"children":[{"number":9,"description":"Given the user is on the EBSA home page","duration":2237,"startTime":1510687967962,"screenshots":[{"screenshot":"ecebda72f278ef6c026b455ca12c55ca.png"},{"screenshot":"27b89e7066e07b7b836933e6a1f8fe28.png"}],"result":"SUCCESS","children":[{"number":10,"description":"On EBSA page","duration":1410,"startTime":1510687968314,"screenshots":[{"screenshot":"ecebda72f278ef6c026b455ca12c55ca.png"},{"screenshot":"b39a28452b0547614e78d4830a0d5334.png"}],"result":"SUCCESS"}]},{"number":11,"description":"When the user clicks on {federalRegister} within the Laws \u0026 Regulations tab on the menu bar","duration":6678,"startTime":1510687970199,"screenshots":[{"screenshot":"27b89e7066e07b7b836933e6a1f8fe28.png"},{"screenshot":"8feac02d8c926982eb68b238c42d854c.png"}],"result":"SUCCESS","children":[{"number":12,"description":"Click nav node: federalRegister","duration":5800,"startTime":1510687970682,"screenshots":[{"screenshot":"27b89e7066e07b7b836933e6a1f8fe28.png"},{"screenshot":"8feac02d8c926982eb68b238c42d854c.png"}],"result":"SUCCESS"}]},{"number":13,"description":"Then the {federalRegister} page should open correctly","duration":1520,"startTime":1510687976877,"screenshots":[{"screenshot":"8feac02d8c926982eb68b238c42d854c.png"}],"result":"SUCCESS","children":[{"number":14,"description":"Should see page: federalRegister","duration":783,"startTime":1510687977255,"screenshots":[{"screenshot":"8feac02d8c926982eb68b238c42d854c.png"}],"result":"SUCCESS"}]}]}],"userStory":{"id":"ebsaRegression","storyName":"Ebsa regression","path":"stories/fullRegression/ebsaRegression.story","narrative":"In order to assert that the basic functionality of https://www.dol.gov/agencies/ebsa is working\nAs a tester\nI want to run the daily regressions at least twice a day\r\n\r\nMeta:","type":"story"},"title":"Verify all of the Laws \u0026 Regulations tabs from the EBSA page","tags":[{"name":"Full regression","type":"feature"},{"name":"Full regression/Ebsa regression","type":"story"}],"startTime":1510687958566,"duration":19832,"sessionId":"74540789c94f1dc2e987c77afec3750f","driver":"chrome","dataTable":{"headers":["lawsregsMenuItem"],"rows":[{"values":["HIPAA"],"result":"SUCCESS"},{"values":["federalRegister"],"result":"SUCCESS"}],"predefinedRows":true,"currentRow":{"value":1},"dataSetDescriptors":[{"startRow":0,"rowCount":0}]},"manual":false,"result":"SUCCESS"}