<acceptance-test-run title="Verify all of the Employers &amp; Advisers tabs from the EBSA page" name="Verify all of the Employers &amp; Advisers tabs from the EBSA page" steps="6" successful="6" failures="0" skipped="0" ignored="0" pending="0" result="SUCCESS" duration="19536" timestamp="2017-11-29T12:28:26.134-05:00" session-id="69ddfc0ab3ec5e49fb4266d921ed55af">
  <user-story id="ebsaRegression" name="Ebsa regression" path="stories/fullRegression/ebsaRegression.story"/>
  <tags>
    <tag name="Full regression" type="feature"/>
    <tag name="Full regression/Ebsa regression" type="story"/>
  </tags>
  <examples>
    <datasets>
      <dataset startRow="0" rowCount="0"/>
    </datasets>
    <headers>
      <header>employerAdviserMenuItem</header>
    </headers>
    <rows>
      <row result="SUCCESS">
        <value>abandonedPlans</value>
      </row>
      <row result="SUCCESS">
        <value>reportingGuidelines</value>
      </row>
    </rows>
  </examples>
  <test-group name="[1] {employerAdviserMenuItem=abandonedPlans}" result="SUCCESS">
    <screenshots>
      <screenshot image="eccf236bcf4b08df9f518eacedc773c5.png"/>
    </screenshots>
    <test-group name="Given the user is on the EBSA home page" result="SUCCESS">
      <screenshots>
        <screenshot image="eccf236bcf4b08df9f518eacedc773c5.png"/>
        <screenshot image="c1dabb473102b5ec9621bb41e98d4923.png"/>
      </screenshots>
      <test-step result="SUCCESS" duration="1479">
        <screenshots>
          <screenshot image="eccf236bcf4b08df9f518eacedc773c5.png"/>
          <screenshot image="1d16f9e34a7bf3fc629c969c4d9f837d.png"/>
        </screenshots>
        <description>On EBSA page</description>
      </test-step>
    </test-group>
    <test-group name="When the user clicks on {abandonedPlans} within the Employers &amp; Advisers tab on the menu bar" result="SUCCESS">
      <screenshots>
        <screenshot image="c1dabb473102b5ec9621bb41e98d4923.png"/>
        <screenshot image="36e06a86f312580febfd6dc98001b7ff.png"/>
      </screenshots>
      <test-step result="SUCCESS" duration="3891">
        <screenshots>
          <screenshot image="c1dabb473102b5ec9621bb41e98d4923.png"/>
          <screenshot image="36e06a86f312580febfd6dc98001b7ff.png"/>
        </screenshots>
        <description>Click nav node: abandonedPlans</description>
      </test-step>
    </test-group>
    <test-group name="Then the {abandonedPlans} page should open correctly" result="SUCCESS">
      <screenshots>
        <screenshot image="36e06a86f312580febfd6dc98001b7ff.png"/>
      </screenshots>
      <test-step result="SUCCESS" duration="853">
        <screenshots>
          <screenshot image="36e06a86f312580febfd6dc98001b7ff.png"/>
        </screenshots>
        <description>Should see page: abandonedPlans</description>
      </test-step>
    </test-group>
  </test-group>
  <test-group name="[2] {employerAdviserMenuItem=reportingGuidelines}" result="SUCCESS">
    <screenshots>
      <screenshot image="36e06a86f312580febfd6dc98001b7ff.png"/>
    </screenshots>
    <test-group name="Given the user is on the EBSA home page" result="SUCCESS">
      <screenshots>
        <screenshot image="36e06a86f312580febfd6dc98001b7ff.png"/>
        <screenshot image="c1dabb473102b5ec9621bb41e98d4923.png"/>
      </screenshots>
      <test-step result="SUCCESS" duration="1426">
        <screenshots>
          <screenshot image="36e06a86f312580febfd6dc98001b7ff.png"/>
          <screenshot image="c94ab9c2db223f817025252aa449fdce.png"/>
        </screenshots>
        <description>On EBSA page</description>
      </test-step>
    </test-group>
    <test-group name="When the user clicks on {reportingGuidelines} within the Employers &amp; Advisers tab on the menu bar" result="SUCCESS">
      <screenshots>
        <screenshot image="c1dabb473102b5ec9621bb41e98d4923.png"/>
        <screenshot image="42108eb1f648f7c2222b376762ea5b64.png"/>
      </screenshots>
      <test-step result="SUCCESS" duration="4890">
        <screenshots>
          <screenshot image="c1dabb473102b5ec9621bb41e98d4923.png"/>
          <screenshot image="42108eb1f648f7c2222b376762ea5b64.png"/>
        </screenshots>
        <description>Click nav node: reportingGuidelines</description>
      </test-step>
    </test-group>
    <test-group name="Then the {reportingGuidelines} page should open correctly" result="SUCCESS">
      <screenshots>
        <screenshot image="42108eb1f648f7c2222b376762ea5b64.png"/>
      </screenshots>
      <test-step result="SUCCESS" duration="1142">
        <screenshots>
          <screenshot image="42108eb1f648f7c2222b376762ea5b64.png"/>
        </screenshots>
        <description>Should see page: reportingGuidelines</description>
      </test-step>
    </test-group>
  </test-group>
</acceptance-test-run>