{"name":"Verify all of the Press sub-navigation tabs open correctly","testSteps":[{"number":1,"description":"[1] {subNavMenuPress\u003dNewsroom}","duration":1,"startTime":1515007657597,"result":"SKIPPED","children":[{"number":2,"description":"Given the user is on the DOL home page","duration":0,"startTime":1515007657597,"result":"SUCCESS"},{"number":3,"description":"When the user clicks on the \u003csubNavMenuPress\u003e within the Press navigation bar","duration":0,"startTime":1515007657597,"result":"SUCCESS"},{"number":4,"description":"Then the \u003csubNavMenuPress\u003e page should open correctly","duration":0,"startTime":1515007657597,"result":"SUCCESS"}]},{"number":5,"description":"[2] {subNavMenuPress\u003dNews Release}","duration":0,"startTime":1515007657598,"result":"SKIPPED","children":[{"number":6,"description":"Given the user is on the DOL home page","duration":0,"startTime":1515007657598,"result":"SUCCESS"},{"number":7,"description":"When the user clicks on the \u003csubNavMenuPress\u003e within the Press navigation bar","duration":0,"startTime":1515007657598,"result":"SUCCESS"},{"number":8,"description":"Then the \u003csubNavMenuPress\u003e page should open correctly","duration":0,"startTime":1515007657598,"result":"SUCCESS"}]},{"number":9,"description":"[3] {subNavMenuPress\u003dNews Letter}","duration":1,"startTime":1515007657598,"result":"SKIPPED","children":[{"number":10,"description":"Given the user is on the DOL home page","duration":0,"startTime":1515007657598,"result":"SUCCESS"},{"number":11,"description":"When the user clicks on the \u003csubNavMenuPress\u003e within the Press navigation bar","duration":0,"startTime":1515007657598,"result":"SUCCESS"},{"number":12,"description":"Then the \u003csubNavMenuPress\u003e page should open correctly","duration":0,"startTime":1515007657598,"result":"SUCCESS"}]}],"userStory":{"id":"dolHomepageRegression","storyName":"Dol homepage regression","path":"stories/fullRegression/dolHomepageRegression.story","narrative":"In order to assert that the basic functionality of https://www.dol.gov/ is working\nAs a tester\nI want to run the daily regressions at least twice a day\n\nMeta:","type":"story"},"title":"Verify all of the Press sub-navigation tabs open correctly","tags":[{"name":"Full regression","type":"feature"},{"name":"Full regression/Dol homepage regression","type":"story"}],"startTime":1515007657596,"duration":0,"annotatedResult":"SKIPPED","dataTable":{"headers":["subNavMenuPress"],"rows":[{"values":["Newsroom"],"result":"SUCCESS"},{"values":["News Release"],"result":"SUCCESS"},{"values":["News Letter"],"result":"SUCCESS"}],"predefinedRows":true,"currentRow":{"value":2},"dataSetDescriptors":[{"startRow":0,"rowCount":0}]},"manual":false,"result":"SKIPPED"}