{"name":"Verify all of the Agencies sub-navigation tabs open correctly","testSteps":[{"number":1,"description":"[1] {subNavMenuAgencies\u003dILAB}","duration":9227,"startTime":1512491191897,"screenshots":[{"screenshot":"5714b5166415e33901405c3f4fdb6c17.png"}],"children":[{"number":2,"description":"Given the user is on the DOL home page","duration":2433,"startTime":1512491192277,"screenshots":[{"screenshot":"5714b5166415e33901405c3f4fdb6c17.png"},{"screenshot":"2b3a9477f51a64588e10c743d0b9d63b.png"}],"result":"SUCCESS","children":[{"number":3,"description":"On home page","duration":1601,"startTime":1512491192680,"screenshots":[{"screenshot":"5714b5166415e33901405c3f4fdb6c17.png"},{"screenshot":"dbbc81cdb151cfc377c0c6d23e0c2e04.png"}],"result":"SUCCESS"}]},{"number":4,"description":"When the user clicks on the {ILAB} within the Agencies navigation bar","duration":4031,"startTime":1512491194710,"screenshots":[{"screenshot":"2b3a9477f51a64588e10c743d0b9d63b.png"},{"screenshot":"2710dc22abfecd1258aeb7fcfce18680.png"}],"result":"SUCCESS","children":[{"number":5,"description":"Click nav node: ILAB","duration":3041,"startTime":1512491195141,"screenshots":[{"screenshot":"2b3a9477f51a64588e10c743d0b9d63b.png"},{"screenshot":"a362f68e3f1d1bbfa8d73d2ff9856f5e.png"}],"result":"SUCCESS"}]},{"number":6,"description":"Then the {ILAB} page should open correctly","duration":2382,"startTime":1512491198742,"screenshots":[{"screenshot":"2710dc22abfecd1258aeb7fcfce18680.png"}],"result":"SUCCESS","children":[{"number":7,"description":"Should see page: ILAB","duration":1225,"startTime":1512491199305,"screenshots":[{"screenshot":"2710dc22abfecd1258aeb7fcfce18680.png"}],"result":"SUCCESS"}]}]},{"number":8,"description":"[2] {subNavMenuAgencies\u003dEBSA}","duration":8848,"startTime":1512491201124,"screenshots":[{"screenshot":"2710dc22abfecd1258aeb7fcfce18680.png"}],"children":[{"number":9,"description":"Given the user is on the DOL home page","duration":2813,"startTime":1512491201698,"screenshots":[{"screenshot":"2710dc22abfecd1258aeb7fcfce18680.png"},{"screenshot":"2b3a9477f51a64588e10c743d0b9d63b.png"}],"result":"SUCCESS","children":[{"number":10,"description":"On home page","duration":1787,"startTime":1512491202281,"screenshots":[{"screenshot":"2710dc22abfecd1258aeb7fcfce18680.png"},{"screenshot":"ecd0dca37e37328b9118be3b1d165ccf.png"}],"result":"SUCCESS"}]},{"number":11,"description":"When the user clicks on the {EBSA} within the Agencies navigation bar","duration":3626,"startTime":1512491204511,"screenshots":[{"screenshot":"2b3a9477f51a64588e10c743d0b9d63b.png"},{"screenshot":"dfc492e0abf6e0f2c4257ef974c44521.png"}],"result":"SUCCESS","children":[{"number":12,"description":"Click nav node: EBSA","duration":2741,"startTime":1512491204942,"screenshots":[{"screenshot":"2b3a9477f51a64588e10c743d0b9d63b.png"},{"screenshot":"937abc1bb7b53fae860c5029034aeba3.png"}],"result":"SUCCESS"}]},{"number":13,"description":"Then the {EBSA} page should open correctly","duration":1835,"startTime":1512491208137,"screenshots":[{"screenshot":"dfc492e0abf6e0f2c4257ef974c44521.png"}],"result":"SUCCESS","children":[{"number":14,"description":"Should see page: EBSA","duration":945,"startTime":1512491208583,"screenshots":[{"screenshot":"dfc492e0abf6e0f2c4257ef974c44521.png"}],"result":"SUCCESS"}]}]}],"userStory":{"id":"dolHomepageRegression","storyName":"Dol homepage regression","path":"stories/fullRegression/dolHomepageRegression.story","narrative":"In order to assert that the basic functionality of https://www.dol.gov/ is working\nAs a tester\nI want to run the daily regressions at least twice a day\r\n\r\nMeta:","type":"story"},"title":"Verify all of the Agencies sub-navigation tabs open correctly","tags":[{"name":"Full regression","type":"feature"},{"name":"Full regression/Dol homepage regression","type":"story"}],"startTime":1512491191895,"duration":18078,"sessionId":"798baad074b04ed2be189fef0acec193","driver":"chrome","dataTable":{"headers":["subNavMenuAgencies"],"rows":[{"values":["ILAB"],"result":"SUCCESS"},{"values":["EBSA"],"result":"SUCCESS"}],"predefinedRows":true,"currentRow":{"value":1},"dataSetDescriptors":[{"startRow":0,"rowCount":0}]},"manual":false,"result":"SUCCESS"}