{"name":"Verify all of the Footer navigation links open correctly","testSteps":[{"number":1,"description":"[1] {navFooterItem\u003dRSS}","duration":7603,"startTime":1514495159450,"screenshots":[{"screenshot":"817940cbe228b1b68960e720060c567a.png"}],"children":[{"number":2,"description":"Given the user is on the DOL home page","duration":2909,"startTime":1514495160136,"screenshots":[{"screenshot":"817940cbe228b1b68960e720060c567a.png"},{"screenshot":"cd9de43749baf4a0073b19406a2114e2.png"}],"result":"SUCCESS","children":[{"number":3,"description":"On home page","duration":1623,"startTime":1514495160824,"screenshots":[{"screenshot":"817940cbe228b1b68960e720060c567a.png"},{"screenshot":"2d9aca64c0aa1bfb8cb8227490886b7a.png"}],"result":"SUCCESS"}]},{"number":4,"description":"When the user clicks on the {RSS} within the Footer","duration":2370,"startTime":1514495163045,"screenshots":[{"screenshot":"cd9de43749baf4a0073b19406a2114e2.png"},{"screenshot":"077f75350326804c8dffc1e125421ad8.png"}],"result":"SUCCESS","children":[{"number":5,"description":"Click nav node: RSS","duration":1382,"startTime":1514495163630,"screenshots":[{"screenshot":"cd9de43749baf4a0073b19406a2114e2.png"},{"screenshot":"077f75350326804c8dffc1e125421ad8.png"}],"result":"SUCCESS"}]},{"number":6,"description":"Then the {RSS} page should open correctly","duration":1637,"startTime":1514495165415,"screenshots":[{"screenshot":"077f75350326804c8dffc1e125421ad8.png"}],"result":"SUCCESS","children":[{"number":7,"description":"Should see page: RSS","duration":835,"startTime":1514495165814,"screenshots":[{"screenshot":"077f75350326804c8dffc1e125421ad8.png"}],"result":"SUCCESS"}]}]},{"number":8,"description":"[2] {navFooterItem\u003dDisclaimer}","duration":6954,"startTime":1514495167053,"screenshots":[{"screenshot":"077f75350326804c8dffc1e125421ad8.png"}],"children":[{"number":9,"description":"Given the user is on the DOL home page","duration":2339,"startTime":1514495167452,"screenshots":[{"screenshot":"077f75350326804c8dffc1e125421ad8.png"},{"screenshot":"cd9de43749baf4a0073b19406a2114e2.png"}],"result":"SUCCESS","children":[{"number":10,"description":"On home page","duration":1333,"startTime":1514495167851,"screenshots":[{"screenshot":"077f75350326804c8dffc1e125421ad8.png"},{"screenshot":"f84589f610637ef15d9e148d1a7e5db1.png"}],"result":"SUCCESS"}]},{"number":11,"description":"When the user clicks on the {Disclaimer} within the Footer","duration":2521,"startTime":1514495169791,"screenshots":[{"screenshot":"cd9de43749baf4a0073b19406a2114e2.png"},{"screenshot":"51277f65949c0bd01e9b1e7dcb40c068.png"}],"result":"SUCCESS","children":[{"number":12,"description":"Click nav node: Disclaimer","duration":1501,"startTime":1514495170386,"screenshots":[{"screenshot":"cd9de43749baf4a0073b19406a2114e2.png"},{"screenshot":"51277f65949c0bd01e9b1e7dcb40c068.png"}],"result":"SUCCESS"}]},{"number":13,"description":"Then the {Disclaimer} page should open correctly","duration":1695,"startTime":1514495172312,"screenshots":[{"screenshot":"51277f65949c0bd01e9b1e7dcb40c068.png"}],"result":"SUCCESS","children":[{"number":14,"description":"Should see page: Disclaimer","duration":859,"startTime":1514495172731,"screenshots":[{"screenshot":"51277f65949c0bd01e9b1e7dcb40c068.png"}],"result":"SUCCESS"}]}]},{"number":15,"description":"[3] {navFooterItem\u003dNFA}","duration":7395,"startTime":1514495174007,"screenshots":[{"screenshot":"51277f65949c0bd01e9b1e7dcb40c068.png"}],"children":[{"number":16,"description":"Given the user is on the DOL home page","duration":2475,"startTime":1514495174425,"screenshots":[{"screenshot":"51277f65949c0bd01e9b1e7dcb40c068.png"},{"screenshot":"cd9de43749baf4a0073b19406a2114e2.png"}],"result":"SUCCESS","children":[{"number":17,"description":"On home page","duration":1455,"startTime":1514495174843,"screenshots":[{"screenshot":"51277f65949c0bd01e9b1e7dcb40c068.png"},{"screenshot":"753bb316f174b37139628f5f340c6ee7.png"}],"result":"SUCCESS"}]},{"number":18,"description":"When the user clicks on the {NFA} within the Footer","duration":2870,"startTime":1514495176900,"screenshots":[{"screenshot":"cd9de43749baf4a0073b19406a2114e2.png"},{"screenshot":"dde15062cd3861ededfd5c84c2982071.png"}],"result":"SUCCESS","children":[{"number":19,"description":"Click nav node: NFA","duration":1865,"startTime":1514495177490,"screenshots":[{"screenshot":"cd9de43749baf4a0073b19406a2114e2.png"},{"screenshot":"dde15062cd3861ededfd5c84c2982071.png"}],"result":"SUCCESS"}]},{"number":20,"description":"Then the {NFA} page should open correctly","duration":1631,"startTime":1514495179770,"screenshots":[{"screenshot":"dde15062cd3861ededfd5c84c2982071.png"}],"result":"SUCCESS","children":[{"number":21,"description":"Should see page: NFA","duration":828,"startTime":1514495180174,"screenshots":[{"screenshot":"dde15062cd3861ededfd5c84c2982071.png"}],"result":"SUCCESS"}]}]},{"number":22,"description":"[4] {navFooterItem\u003dPSS}","duration":7220,"startTime":1514495181402,"screenshots":[{"screenshot":"dde15062cd3861ededfd5c84c2982071.png"}],"children":[{"number":23,"description":"Given the user is on the DOL home page","duration":2400,"startTime":1514495181804,"screenshots":[{"screenshot":"dde15062cd3861ededfd5c84c2982071.png"},{"screenshot":"cd9de43749baf4a0073b19406a2114e2.png"}],"result":"SUCCESS","children":[{"number":24,"description":"On home page","duration":1401,"startTime":1514495182210,"screenshots":[{"screenshot":"dde15062cd3861ededfd5c84c2982071.png"},{"screenshot":"d37b509d891a0269354e70232f10d826.png"}],"result":"SUCCESS"}]},{"number":25,"description":"When the user clicks on the {PSS} within the Footer","duration":2634,"startTime":1514495184204,"screenshots":[{"screenshot":"cd9de43749baf4a0073b19406a2114e2.png"},{"screenshot":"f6a60d1911aef1df8505de4f742b69ea.png"}],"result":"SUCCESS","children":[{"number":26,"description":"Click nav node: PSS","duration":1586,"startTime":1514495184805,"screenshots":[{"screenshot":"cd9de43749baf4a0073b19406a2114e2.png"},{"screenshot":"f6a60d1911aef1df8505de4f742b69ea.png"}],"result":"SUCCESS"}]},{"number":27,"description":"Then the {PSS} page should open correctly","duration":1784,"startTime":1514495186838,"screenshots":[{"screenshot":"f6a60d1911aef1df8505de4f742b69ea.png"}],"result":"SUCCESS","children":[{"number":28,"description":"Should see page: PSS","duration":901,"startTime":1514495187284,"screenshots":[{"screenshot":"f6a60d1911aef1df8505de4f742b69ea.png"}],"result":"SUCCESS"}]}]},{"number":29,"description":"[5] {navFooterItem\u003dFOIA}","duration":7125,"startTime":1514495188622,"screenshots":[{"screenshot":"f6a60d1911aef1df8505de4f742b69ea.png"}],"children":[{"number":30,"description":"Given the user is on the DOL home page","duration":2460,"startTime":1514495189051,"screenshots":[{"screenshot":"f6a60d1911aef1df8505de4f742b69ea.png"},{"screenshot":"cd9de43749baf4a0073b19406a2114e2.png"}],"result":"SUCCESS","children":[{"number":31,"description":"On home page","duration":1424,"startTime":1514495189484,"screenshots":[{"screenshot":"f6a60d1911aef1df8505de4f742b69ea.png"},{"screenshot":"f84589f610637ef15d9e148d1a7e5db1.png"}],"result":"SUCCESS"}]},{"number":32,"description":"When the user clicks on the {FOIA} within the Footer","duration":2508,"startTime":1514495191511,"screenshots":[{"screenshot":"cd9de43749baf4a0073b19406a2114e2.png"},{"screenshot":"d4411defde3266e96c23ca01fe1076de.png"}],"result":"SUCCESS","children":[{"number":33,"description":"Click nav node: FOIA","duration":1485,"startTime":1514495192107,"screenshots":[{"screenshot":"cd9de43749baf4a0073b19406a2114e2.png"},{"screenshot":"d4411defde3266e96c23ca01fe1076de.png"}],"result":"SUCCESS"}]},{"number":34,"description":"Then the {FOIA} page should open correctly","duration":1727,"startTime":1514495194019,"screenshots":[{"screenshot":"d4411defde3266e96c23ca01fe1076de.png"}],"result":"SUCCESS","children":[{"number":35,"description":"Should see page: FOIA","duration":877,"startTime":1514495194445,"screenshots":[{"screenshot":"d4411defde3266e96c23ca01fe1076de.png"}],"result":"SUCCESS"}]}]},{"number":36,"description":"[6] {navFooterItem\u003dTTY}","duration":6937,"startTime":1514495195747,"screenshots":[{"screenshot":"d4411defde3266e96c23ca01fe1076de.png"}],"children":[{"number":37,"description":"Given the user is on the DOL home page","duration":2321,"startTime":1514495196167,"screenshots":[{"screenshot":"d4411defde3266e96c23ca01fe1076de.png"},{"screenshot":"cd9de43749baf4a0073b19406a2114e2.png"}],"result":"SUCCESS","children":[{"number":38,"description":"On home page","duration":1304,"startTime":1514495196591,"screenshots":[{"screenshot":"d4411defde3266e96c23ca01fe1076de.png"},{"screenshot":"24be975586ace982ede17fc997202712.png"}],"result":"SUCCESS"}]},{"number":39,"description":"When the user clicks on the {TTY} within the Footer","duration":2527,"startTime":1514495198488,"screenshots":[{"screenshot":"cd9de43749baf4a0073b19406a2114e2.png"},{"screenshot":"b16e568ff7fe36f6672973f99042d14a.png"}],"result":"SUCCESS","children":[{"number":40,"description":"Click nav node: TTY","duration":1521,"startTime":1514495199085,"screenshots":[{"screenshot":"cd9de43749baf4a0073b19406a2114e2.png"},{"screenshot":"b16e568ff7fe36f6672973f99042d14a.png"}],"result":"SUCCESS"}]},{"number":41,"description":"Then the {TTY} page should open correctly","duration":1669,"startTime":1514495201015,"screenshots":[{"screenshot":"b16e568ff7fe36f6672973f99042d14a.png"}],"result":"SUCCESS","children":[{"number":42,"description":"Should see page: TTY","duration":842,"startTime":1514495201430,"screenshots":[{"screenshot":"b16e568ff7fe36f6672973f99042d14a.png"}],"result":"SUCCESS"}]}]}],"userStory":{"id":"dolHomepageRegression","storyName":"Dol homepage regression","path":"stories/fullRegression/dolHomepageRegression.story","narrative":"In order to assert that the basic functionality of https://www.dol.gov/ is working\nAs a tester\nI want to run the daily regressions at least twice a day\n\nMeta:","type":"story"},"title":"Verify all of the Footer navigation links open correctly","tags":[{"name":"Full regression","type":"feature"},{"name":"Full regression/Dol homepage regression","type":"story"}],"startTime":1514495159449,"duration":43236,"sessionId":"f275d52caf44083ea235fd42a890c86c","driver":"chrome","dataTable":{"headers":["navFooterItem"],"rows":[{"values":["RSS"],"result":"SUCCESS"},{"values":["Disclaimer"],"result":"SUCCESS"},{"values":["NFA"],"result":"SUCCESS"},{"values":["PSS"],"result":"SUCCESS"},{"values":["FOIA"],"result":"SUCCESS"},{"values":["TTY"],"result":"SUCCESS"}],"predefinedRows":true,"currentRow":{"value":5},"dataSetDescriptors":[{"startRow":0,"rowCount":0}]},"manual":false,"result":"SUCCESS"}