{"name":"Verify all of the navbar tabs to assert that the pages open correctly","testSteps":[{"number":1,"description":"[1] {navMenuItem\u003dTopics}","duration":11446,"startTime":1507150765887,"children":[{"number":2,"description":"Given the user is on the DOL home page","duration":7844,"startTime":1507150765887,"screenshots":[{"screenshot":"a6eea46759c1399e390038c876ad061b.png"}],"result":"SUCCESS","children":[{"number":3,"description":"On home page","duration":3815,"startTime":1507150769439,"screenshots":[{"screenshot":"821aec7c340d4517e842fb3ee26b105b.png"},{"screenshot":"a6eea46759c1399e390038c876ad061b.png"}],"result":"SUCCESS"}]},{"number":4,"description":"When the user clicks on {Topics} within the top navigation bar","duration":2149,"startTime":1507150773731,"screenshots":[{"screenshot":"a6eea46759c1399e390038c876ad061b.png"},{"screenshot":"d304f47aad6c608054fc19498e681ff0.png"}],"result":"SUCCESS","children":[{"number":5,"description":"Click nav node: Topics","duration":1340,"startTime":1507150774162,"screenshots":[{"screenshot":"a6eea46759c1399e390038c876ad061b.png"},{"screenshot":"d304f47aad6c608054fc19498e681ff0.png"}],"result":"SUCCESS"}]},{"number":6,"description":"Then the {Topics} page should open correctly","duration":1453,"startTime":1507150775880,"screenshots":[{"screenshot":"d304f47aad6c608054fc19498e681ff0.png"}],"result":"SUCCESS","children":[{"number":7,"description":"Should see page: Topics","duration":733,"startTime":1507150776249,"screenshots":[{"screenshot":"d304f47aad6c608054fc19498e681ff0.png"}],"result":"SUCCESS"}]}]},{"number":8,"description":"[2] {navMenuItem\u003dAgencies}","duration":6243,"startTime":1507150777333,"screenshots":[{"screenshot":"d304f47aad6c608054fc19498e681ff0.png"}],"children":[{"number":9,"description":"Given the user is on the DOL home page","duration":2315,"startTime":1507150777704,"screenshots":[{"screenshot":"d304f47aad6c608054fc19498e681ff0.png"},{"screenshot":"a6eea46759c1399e390038c876ad061b.png"}],"result":"SUCCESS","children":[{"number":10,"description":"On home page","duration":1491,"startTime":1507150778035,"screenshots":[{"screenshot":"d304f47aad6c608054fc19498e681ff0.png"},{"screenshot":"9d9f178a2509120766a54a8fd0d497f4.png"}],"result":"SUCCESS"}]},{"number":11,"description":"When the user clicks on {Agencies} within the top navigation bar","duration":2152,"startTime":1507150780019,"screenshots":[{"screenshot":"a6eea46759c1399e390038c876ad061b.png"},{"screenshot":"a94f9a1a59cbea4506d52ce153378270.png"}],"result":"SUCCESS","children":[{"number":12,"description":"Click nav node: Agencies","duration":1317,"startTime":1507150780505,"screenshots":[{"screenshot":"a6eea46759c1399e390038c876ad061b.png"},{"screenshot":"a94f9a1a59cbea4506d52ce153378270.png"}],"result":"SUCCESS"}]},{"number":13,"description":"Then the {Agencies} page should open correctly","duration":1405,"startTime":1507150782171,"screenshots":[{"screenshot":"a94f9a1a59cbea4506d52ce153378270.png"}],"result":"SUCCESS","children":[{"number":14,"description":"Should see page: Agencies","duration":708,"startTime":1507150782523,"screenshots":[{"screenshot":"a94f9a1a59cbea4506d52ce153378270.png"}],"result":"SUCCESS"}]}]},{"number":15,"description":"[3] {navMenuItem\u003dForms}","duration":6168,"startTime":1507150783576,"screenshots":[{"screenshot":"a94f9a1a59cbea4506d52ce153378270.png"}],"children":[{"number":16,"description":"Given the user is on the DOL home page","duration":2181,"startTime":1507150783925,"screenshots":[{"screenshot":"a94f9a1a59cbea4506d52ce153378270.png"},{"screenshot":"a6eea46759c1399e390038c876ad061b.png"}],"result":"SUCCESS","children":[{"number":17,"description":"On home page","duration":1379,"startTime":1507150784302,"screenshots":[{"screenshot":"a94f9a1a59cbea4506d52ce153378270.png"},{"screenshot":"e1409646343e8dfadd08f1e74e05d262.png"}],"result":"SUCCESS"}]},{"number":18,"description":"When the user clicks on {Forms} within the top navigation bar","duration":2172,"startTime":1507150786106,"screenshots":[{"screenshot":"a6eea46759c1399e390038c876ad061b.png"},{"screenshot":"1224421cad94265b2116a59b9fb78fc6.png"}],"result":"SUCCESS","children":[{"number":19,"description":"Click nav node: Forms","duration":1402,"startTime":1507150786528,"screenshots":[{"screenshot":"a6eea46759c1399e390038c876ad061b.png"},{"screenshot":"1224421cad94265b2116a59b9fb78fc6.png"}],"result":"SUCCESS"}]},{"number":20,"description":"Then the {Forms} page should open correctly","duration":1466,"startTime":1507150788278,"screenshots":[{"screenshot":"1224421cad94265b2116a59b9fb78fc6.png"}],"result":"SUCCESS","children":[{"number":21,"description":"Should see page: Forms","duration":739,"startTime":1507150788665,"screenshots":[{"screenshot":"1224421cad94265b2116a59b9fb78fc6.png"}],"result":"SUCCESS"}]}]},{"number":22,"description":"[4] {navMenuItem\u003dFAQ}","duration":6297,"startTime":1507150789744,"screenshots":[{"screenshot":"1224421cad94265b2116a59b9fb78fc6.png"}],"children":[{"number":23,"description":"Given the user is on the DOL home page","duration":2164,"startTime":1507150790089,"screenshots":[{"screenshot":"1224421cad94265b2116a59b9fb78fc6.png"},{"screenshot":"a6eea46759c1399e390038c876ad061b.png"}],"result":"SUCCESS","children":[{"number":24,"description":"On home page","duration":1384,"startTime":1507150790451,"screenshots":[{"screenshot":"1224421cad94265b2116a59b9fb78fc6.png"},{"screenshot":"c8913cb3a8db92424ed02faea07e8e4e.png"}],"result":"SUCCESS"}]},{"number":25,"description":"When the user clicks on {FAQ} within the top navigation bar","duration":2387,"startTime":1507150792253,"screenshots":[{"screenshot":"a6eea46759c1399e390038c876ad061b.png"},{"screenshot":"9387d83dbf497b336ac611a38c1f2672.png"}],"result":"SUCCESS","children":[{"number":26,"description":"Click nav node: FAQ","duration":1625,"startTime":1507150792683,"screenshots":[{"screenshot":"a6eea46759c1399e390038c876ad061b.png"},{"screenshot":"9387d83dbf497b336ac611a38c1f2672.png"}],"result":"SUCCESS"}]},{"number":27,"description":"Then the {FAQ} page should open correctly","duration":1401,"startTime":1507150794640,"screenshots":[{"screenshot":"9387d83dbf497b336ac611a38c1f2672.png"}],"result":"SUCCESS","children":[{"number":28,"description":"Should see page: FAQ","duration":694,"startTime":1507150794998,"screenshots":[{"screenshot":"9387d83dbf497b336ac611a38c1f2672.png"}],"result":"SUCCESS"}]}]},{"number":29,"description":"[5] {navMenuItem\u003dAbout}","duration":6180,"startTime":1507150796041,"screenshots":[{"screenshot":"9387d83dbf497b336ac611a38c1f2672.png"}],"children":[{"number":30,"description":"Given the user is on the DOL home page","duration":2110,"startTime":1507150796367,"screenshots":[{"screenshot":"9387d83dbf497b336ac611a38c1f2672.png"},{"screenshot":"a6eea46759c1399e390038c876ad061b.png"}],"result":"SUCCESS","children":[{"number":31,"description":"On home page","duration":1288,"startTime":1507150796730,"screenshots":[{"screenshot":"9387d83dbf497b336ac611a38c1f2672.png"},{"screenshot":"995a170798c6ed95da29548ea1be7f24.png"}],"result":"SUCCESS"}]},{"number":32,"description":"When the user clicks on {About} within the top navigation bar","duration":2290,"startTime":1507150798477,"screenshots":[{"screenshot":"a6eea46759c1399e390038c876ad061b.png"},{"screenshot":"da1435ac000220b844f03078553b68db.png"}],"result":"SUCCESS","children":[{"number":33,"description":"Click nav node: About","duration":1508,"startTime":1507150798909,"screenshots":[{"screenshot":"a6eea46759c1399e390038c876ad061b.png"},{"screenshot":"da1435ac000220b844f03078553b68db.png"}],"result":"SUCCESS"}]},{"number":34,"description":"Then the {About} page should open correctly","duration":1454,"startTime":1507150800767,"screenshots":[{"screenshot":"da1435ac000220b844f03078553b68db.png"}],"result":"SUCCESS","children":[{"number":35,"description":"Should see page: About","duration":742,"startTime":1507150801116,"screenshots":[{"screenshot":"da1435ac000220b844f03078553b68db.png"}],"result":"SUCCESS"}]}]},{"number":36,"description":"[6] {navMenuItem\u003dPress}","duration":9906,"startTime":1507150802221,"screenshots":[{"screenshot":"da1435ac000220b844f03078553b68db.png"}],"children":[{"number":37,"description":"Given the user is on the DOL home page","duration":2077,"startTime":1507150802580,"screenshots":[{"screenshot":"da1435ac000220b844f03078553b68db.png"},{"screenshot":"a6eea46759c1399e390038c876ad061b.png"}],"result":"SUCCESS","children":[{"number":38,"description":"On home page","duration":1308,"startTime":1507150802936,"screenshots":[{"screenshot":"da1435ac000220b844f03078553b68db.png"},{"screenshot":"2a97e9430ce01bc9adf41a47d50fc485.png"}],"result":"SUCCESS"}]},{"number":39,"description":"When the user clicks on {Press} within the top navigation bar","duration":4303,"startTime":1507150804657,"screenshots":[{"screenshot":"a6eea46759c1399e390038c876ad061b.png"},{"screenshot":"80ee00cba9f54e180d030be2eb6f5f98.png"}],"result":"SUCCESS","children":[{"number":40,"description":"Click nav node: Press","duration":3143,"startTime":1507150805069,"screenshots":[{"screenshot":"a6eea46759c1399e390038c876ad061b.png"},{"screenshot":"80ee00cba9f54e180d030be2eb6f5f98.png"}],"result":"SUCCESS"}]},{"number":41,"description":"Then the {Press} page should open correctly","duration":3166,"startTime":1507150808961,"screenshots":[{"screenshot":"80ee00cba9f54e180d030be2eb6f5f98.png"}],"result":"SUCCESS","children":[{"number":42,"description":"Should see page: Press","duration":1603,"startTime":1507150809725,"screenshots":[{"screenshot":"80ee00cba9f54e180d030be2eb6f5f98.png"}],"result":"SUCCESS"}]}]},{"number":43,"description":"[7] {navMenuItem\u003dContact}","duration":7304,"startTime":1507150812143,"screenshots":[{"screenshot":"80ee00cba9f54e180d030be2eb6f5f98.png"}],"children":[{"number":44,"description":"Given the user is on the DOL home page","duration":2967,"startTime":1507150812878,"screenshots":[{"screenshot":"80ee00cba9f54e180d030be2eb6f5f98.png"},{"screenshot":"a6eea46759c1399e390038c876ad061b.png"}],"result":"SUCCESS","children":[{"number":45,"description":"On home page","duration":1772,"startTime":1507150813611,"screenshots":[{"screenshot":"80ee00cba9f54e180d030be2eb6f5f98.png"},{"screenshot":"733b0d68bcd81796a58d35f8eee35077.png"}],"result":"SUCCESS"}]},{"number":46,"description":"When the user clicks on {Contact} within the top navigation bar","duration":2161,"startTime":1507150815845,"screenshots":[{"screenshot":"a6eea46759c1399e390038c876ad061b.png"},{"screenshot":"3e0a5adcaa2f40504351e36449c891e7.png"}],"result":"SUCCESS","children":[{"number":47,"description":"Click nav node: Contact","duration":1382,"startTime":1507150816266,"screenshots":[{"screenshot":"a6eea46759c1399e390038c876ad061b.png"},{"screenshot":"3e0a5adcaa2f40504351e36449c891e7.png"}],"result":"SUCCESS"}]},{"number":48,"description":"Then the {Contact} page should open correctly","duration":1441,"startTime":1507150818006,"screenshots":[{"screenshot":"3e0a5adcaa2f40504351e36449c891e7.png"}],"result":"SUCCESS","children":[{"number":49,"description":"Should see page: Contact","duration":759,"startTime":1507150818348,"screenshots":[{"screenshot":"3e0a5adcaa2f40504351e36449c891e7.png"}],"result":"SUCCESS"}]}]}],"userStory":{"id":"dolHomepageRegression","storyName":"Dol homepage regression","path":"stories/fullRegression/dolHomepageRegression.story","narrative":"In order to assert that the basic functionality of https://www.dol.gov/ is working\nAs a tester\nI want to run the daily regressions at least twice a day\r\n\r\nMeta:","type":"story"},"title":"Verify all of the navbar tabs to assert that the pages open correctly","tags":[{"name":"Full regression","type":"feature"},{"name":"Full regression/Dol homepage regression","type":"story"}],"startTime":1507150765887,"duration":53560,"sessionId":"923bc12a0f6105fdd0f464983e7d5a00","driver":"chrome","dataTable":{"headers":["navMenuItem"],"rows":[{"values":["Topics"],"result":"SUCCESS"},{"values":["Agencies"],"result":"SUCCESS"},{"values":["Forms"],"result":"SUCCESS"},{"values":["FAQ"],"result":"SUCCESS"},{"values":["About"],"result":"SUCCESS"},{"values":["Press"],"result":"SUCCESS"},{"values":["Contact"],"result":"SUCCESS"}],"predefinedRows":true,"currentRow":{"value":6},"dataSetDescriptors":[{"startRow":0,"rowCount":0}]},"manual":false,"result":"SUCCESS"}